{"vocabInfos":[{"lsjDefs":"<b> καταλᾰλ-ιά</b>, ἡ, <br /> <b>evil report, slander</b>, [<a href=\"javascript:void(0)\" title=\" LXX.Wis.1.11, NT.1Pet.2.1 (_plural_). \">LXX+NT</a>]","strongNumber":"G2636","accentedUnicode":"καταλαλιά","relatedNos":[{"strongNumber":"G2635","matchingForm":"καταλαλέω","stepTransliteration":"katalaleō","gloss":"to slander","_zh_tw_Gloss":"毀謗","_es_Gloss":"calumniar","_zh_Gloss":"毁谤"},{"strongNumber":"G2637","matchingForm":"κατάλαλος","stepTransliteration":"katalalos","gloss":"slanderous","_zh_tw_Gloss":"背後說人","_es_Gloss":"calumniador","_zh_Gloss":"背后说人"}],"shortDef":"slander, defamation, evil speech","mediumDef":"slander, defamation, evil speech <br /><b>evil-speaking, detraction, backbiting, slandering, evil speech, defamation </b> <ref='2Co.12.20'>2Cor. 12:20;</ref> <ref='1Pe.2.1'>1Pet. 2:1</ref>*","stepGloss":"slander","stepTransliteration":"katalalia","count":2,"_es_Definition":"calumnia, insulto","_zh_tw_Definition":"惡言, 攻訐, 毀謗 (林後 12:20; 彼前 2:1)","_zh_Definition":"恶言, 攻讦, 毁谤 (林后 12:20; 彼前 2:1)","_step_Type":"word","_vi_Definition":"sự vu khống ; sự gièm pha","_zh_tw_Gloss":"毀謗, 毀謗話","_es_Gloss":"calumnia ","_zh_Gloss":"毁谤, 毁谤话"}]}