{"vocabInfos":[{"strongNumber":"H1265","accentedUnicode":"בְּרוֹשׁ","relatedNos":[{"strongNumber":"H1266","matchingForm":"בְּרוֹת","stepTransliteration":"be.rot","gloss":"cypress","_zh_tw_Gloss":"以松木","_zh_Gloss":"以松木"},{"strongNumber":"H1306","matchingForm":"בִּרְשַׁע","stepTransliteration":"bir.sha","gloss":"Birsha","_searchResultRange":"Gen.14.2","_zh_tw_Gloss":"比沙","_es_Gloss":"Birsha","_zh_Gloss":"比沙"}],"mediumDef":"1) cypress, fir, juniper, pine<br>1a) a noble tree (lit.)<br>1b) of stateliness (fig.)<br>1c) material for temple","stepGloss":"cypress","stepTransliteration":"be.rosh","count":20,"_es_Definition":"¿pino? ¿ciprés?","_zh_tw_Definition":"1)柏樹, 樅樹 <br>   1a) 高華的樹木 <br>   1b) 茂盛, 高大 (比喻用法)<br>   1c) 建殿, 造船, 製做樂器的木材","_zh_Definition":"1)柏树, 枞树 <br>   1a) 高华的树木 <br>   1b) 茂盛, 高大 (比喻用法)<br>   1c) 建殿, 造船, 制做乐器的木材","_step_Type":"word","_zh_tw_Gloss":"松樹","_es_Gloss":"haya","_zh_Gloss":"松树"}]}