{"augmentedStrong" : [{"augmentedStrong": "H1793A", "references": "*"}, {"augmentedStrong": "H1793B", "references": "Ps.90.3"}],"vocabinfos": [{"strongNumber":"H1793A","accentedUnicode":"דַּכָּא","relatedNos":"[{'strongNumber': 'H1792', 'matchingForm': 'דָּכָא', 'stepTransliteration': 'da.kha', 'gloss': 'to crush', '_zh_tw_Gloss': '壓碎', '_es_Gloss': 'quebrantados', '_zh_Gloss': '压碎'}, {'strongNumber': 'H1793B', 'matchingForm': 'דַּכָּא', 'stepTransliteration': 'dak.ka', 'gloss': 'dust', '_zh_tw_Gloss': '塵土, 痛悔', '_es_Gloss': 'quebrantado', '_zh_Gloss': '尘土, 痛悔'}, {'strongNumber': 'H1795', 'matchingForm': 'דַּכָּה', 'stepTransliteration': 'dak.kah', 'gloss': 'crushing', '_zh_tw_Gloss': '痛悔', '_zh_Gloss': '痛悔'}]","mediumDef":"adj<br> contrite<BR> § adj<br> contrite","stepGloss":"contrite","stepTransliteration":"dak.ka","count":2,"_es_Definition":"polvo; (a)   humillado","_zh_tw_Definition":"陽性名詞<br>1) (成為粉末) 塵土 (詩90:3)<br>形容詞<br>2) (破碎) 痛悔的 (詩34:18;賽57:15)","_zh_Definition":"阳性名词<br>1) (成为粉末) 尘土 (诗90:3)<br>形容词<br>2) (破碎) 痛悔的 (诗34:18;赛57:15)","_step_Type":"word","_zh_tw_Gloss":"塵土, 痛悔","_es_Gloss":"quebrantado","_zh_Gloss":"尘土, 痛悔"},{"strongNumber":"H1793B","accentedUnicode":"=","relatedNos":"[{'strongNumber': 'H1792', 'matchingForm': 'דָּכָא', 'stepTransliteration': 'da.kha', 'gloss': 'to crush', '_zh_tw_Gloss': '壓碎', '_es_Gloss': 'quebrantados', '_zh_Gloss': '压碎'}, {'strongNumber': 'H1793A', 'matchingForm': 'דַּכָּא', 'stepTransliteration': 'dak.ka', 'gloss': 'contrite', '_zh_tw_Gloss': '塵土, 痛悔', '_es_Gloss': 'quebrantado', '_zh_Gloss': '尘土, 痛悔'}, {'strongNumber': 'H1795', 'matchingForm': 'דַּכָּה', 'stepTransliteration': 'dak.kah', 'gloss': 'crushing', '_zh_tw_Gloss': '痛悔', '_zh_Gloss': '痛悔'}]","mediumDef":"dust<BR> § dust","stepGloss":"dust","stepTransliteration":"=","count":1,"_es_Definition":"=","_zh_tw_Definition":"=","_zh_Definition":"=","_step_Type":"=","_zh_tw_Gloss":"=","_es_Gloss":"=","_zh_Gloss":"="}]}