{"vocabInfos":[{"strongNumber":"H2338","accentedUnicode":"חוּט","relatedNos":[{"strongNumber":"H2339","matchingForm":"חוּט","stepTransliteration":"chut","gloss":"thread","_zh_tw_Gloss":"線, 一根線","_es_Gloss":"hilo","_zh_Gloss":"线, 一根线"},{"strongNumber":"H2358","matchingForm":"חִוָּר","stepTransliteration":"chiv.var","gloss":"white","_zh_tw_Gloss":"潔白","_es_Gloss":"blanco","_zh_Gloss":"洁白"}],"mediumDef":"(Aphel) to repair, join","stepGloss":"to repair","stepTransliteration":"chut","count":1,"_zh_tw_Definition":"(Aphel) 修復, 連接 #拉 4:12|","_zh_Definition":"(Aphel) 修复, 连接 #拉 4:12|","_step_Type":"verb","_zh_tw_Gloss":"在修理","_zh_Gloss":"在修理"}]}