{"augmentedStrong" : [{"augmentedStrong": "H3823A", "references": "Job.11.12 Song.4.9"}, {"augmentedStrong": "H3823B", "references": "*"}],"vocabinfos": [{"strongNumber":"H3823A","accentedUnicode":"לָבַב","relatedNos":"[{'strongNumber': 'H3820A', 'matchingForm': 'לֵב', 'stepTransliteration': 'lev', 'gloss': 'heart', '_zh_tw_Gloss': '心, 心中', '_es_Gloss': 'corazón', '_zh_Gloss': '心, 心中'}, {'strongNumber': 'H3820B', 'matchingForm': 'לֵב', 'stepTransliteration': 'lev', 'gloss': 'Leb', '_searchResultRange': 'Jer.51.1', '_zh_tw_Gloss': '心, 心中', '_es_Gloss': 'corazón', '_zh_Gloss': '心, 心中'}, {'strongNumber': 'H3823B', 'matchingForm': 'לִבֵּב', 'stepTransliteration': 'lib.bev', 'gloss': 'to bake', '_zh_tw_Gloss': '奪了我心, 當有知識', '_es_Gloss': 'corazón', '_zh_Gloss': '夺了我心, 当有知识'}, {'strongNumber': 'H3824', 'matchingForm': 'לֵבָב', 'stepTransliteration': 'le.vav', 'gloss': 'heart', '_zh_tw_Gloss': '心', '_es_Gloss': 'corazón', '_zh_Gloss': '心'}, {'strongNumber': 'H3826', 'matchingForm': 'לִבָּה', 'stepTransliteration': 'lib.bah', 'gloss': 'heart', '_zh_tw_Gloss': '人心', '_es_Gloss': 'corazones', '_zh_Gloss': '人心'}, {'strongNumber': 'H3834', 'matchingForm': 'לְבִבָה', 'stepTransliteration': 'le.vi.vah', 'gloss': 'cake', '_zh_tw_Gloss': '餅', '_es_Gloss': 'hojuelas', '_zh_Gloss': '饼'}, {'strongNumber': 'H6965A', 'matchingForm': 'קָמָי', 'stepTransliteration': 'qa.ma', 'gloss': '-kamai', '_searchResultRange': 'Jer.51.1', '_zh_tw_Gloss': '起來, 就起來', '_es_Gloss': 'Levántate', '_zh_Gloss': '起来, 就起来'}, {'strongNumber': 'H6965B', 'matchingForm': 'קוּם', 'stepTransliteration': 'qum', 'gloss': 'to arise: rise', '_zh_tw_Gloss': '起來, 就起來', '_es_Gloss': 'Levántate', '_zh_Gloss': '起来, 就起来'}, {'strongNumber': 'H6965H', 'matchingForm': 'קוּם', 'stepTransliteration': 'qum', 'gloss': 'to arise: raise', '_zh_tw_Gloss': '起來, 就起來', '_es_Gloss': 'Levántate', '_zh_Gloss': '起来, 就起来'}, {'strongNumber': 'H6965I', 'matchingForm': 'קוּם', 'stepTransliteration': 'qum', 'gloss': 'to arise: establish', '_zh_tw_Gloss': '起來, 就起來', '_es_Gloss': 'Levántate', '_zh_Gloss': '起来, 就起来'}, {'strongNumber': 'H6965J', 'matchingForm': 'קוּם', 'stepTransliteration': 'qum', 'gloss': 'to arise: attack', '_zh_tw_Gloss': '起來, 就起來', '_es_Gloss': 'Levántate', '_zh_Gloss': '起来, 就起来'}, {'strongNumber': 'H6965K', 'matchingForm': 'קוּם', 'stepTransliteration': 'qum', 'gloss': 'to arise: guard', '_zh_tw_Gloss': '起來, 就起來', '_es_Gloss': 'Levántate', '_zh_Gloss': '起来, 就起来'}]","mediumDef":"1) to ravish, become intelligent, get a mind<br>1a) (Niphal) to take heart, become enheartened, become intelligent<br>1b) (Piel) to ravish the heart, encourage, make heart beat faster<BR> § 1) to ravish, become intelligent, get a mind<br>1a) (Niphal) to take heart, become enheartened, become intelligent<br>1b) (Piel) to ravish the heart, encourage, make heart beat faster","stepGloss":"to encourage","stepTransliteration":"la.vav","count":3,"_es_Definition":"(a) nif.   ser hecho inteligente; (b) pi.   hacer latir el corazón; (c)   cocer lebibot (tortas amasadas)","_zh_tw_Definition":"1) 神魂顛倒, 變聰明, 有心思<br>   1a) (Niphal) 有心思 (伯 11:12)<br>   1b) (Piel) 神魂顛倒, 鼓舞 (歌 4:9)<br>2) (Piel) 作餅, 烘培糕點, 作麵包 (撒下 13:6,8)","_zh_Definition":"1) 神魂颠倒, 变聪明, 有心思<br>   1a) (Niphal) 有心思 (伯 11:12)<br>   1b) (Piel) 神魂颠倒, 鼓舞 (歌 4:9)<br>2) (Piel) 作饼, 烘培糕点, 作面包 (撒下 13:6,8)","_step_Type":"verb","_zh_tw_Gloss":"奪了我心, 當有知識","_es_Gloss":"corazón","_zh_Gloss":"夺了我心, 当有知识"},{"strongNumber":"H3823B","accentedUnicode":"לִבֵּב","relatedNos":"[{'strongNumber': 'H3820A', 'matchingForm': 'לֵב', 'stepTransliteration': 'lev', 'gloss': 'heart', '_zh_tw_Gloss': '心, 心中', '_es_Gloss': 'corazón', '_zh_Gloss': '心, 心中'}, {'strongNumber': 'H3820B', 'matchingForm': 'לֵב', 'stepTransliteration': 'lev', 'gloss': 'Leb', '_searchResultRange': 'Jer.51.1', '_zh_tw_Gloss': '心, 心中', '_es_Gloss': 'corazón', '_zh_Gloss': '心, 心中'}, {'strongNumber': 'H3823A', 'matchingForm': 'לָבַב', 'stepTransliteration': 'la.vav', 'gloss': 'to encourage', '_zh_tw_Gloss': '奪了我心, 當有知識', '_es_Gloss': 'corazón', '_zh_Gloss': '夺了我心, 当有知识'}, {'strongNumber': 'H3824', 'matchingForm': 'לֵבָב', 'stepTransliteration': 'le.vav', 'gloss': 'heart', '_zh_tw_Gloss': '心', '_es_Gloss': 'corazón', '_zh_Gloss': '心'}, {'strongNumber': 'H3826', 'matchingForm': 'לִבָּה', 'stepTransliteration': 'lib.bah', 'gloss': 'heart', '_zh_tw_Gloss': '人心', '_es_Gloss': 'corazones', '_zh_Gloss': '人心'}, {'strongNumber': 'H3834', 'matchingForm': 'לְבִבָה', 'stepTransliteration': 'le.vi.vah', 'gloss': 'cake', '_zh_tw_Gloss': '餅', '_es_Gloss': 'hojuelas', '_zh_Gloss': '饼'}, {'strongNumber': 'H6965A', 'matchingForm': 'קָמָי', 'stepTransliteration': 'qa.ma', 'gloss': '-kamai', '_searchResultRange': 'Jer.51.1', '_zh_tw_Gloss': '起來, 就起來', '_es_Gloss': 'Levántate', '_zh_Gloss': '起来, 就起来'}, {'strongNumber': 'H6965B', 'matchingForm': 'קוּם', 'stepTransliteration': 'qum', 'gloss': 'to arise: rise', '_zh_tw_Gloss': '起來, 就起來', '_es_Gloss': 'Levántate', '_zh_Gloss': '起来, 就起来'}, {'strongNumber': 'H6965H', 'matchingForm': 'קוּם', 'stepTransliteration': 'qum', 'gloss': 'to arise: raise', '_zh_tw_Gloss': '起來, 就起來', '_es_Gloss': 'Levántate', '_zh_Gloss': '起来, 就起来'}, {'strongNumber': 'H6965I', 'matchingForm': 'קוּם', 'stepTransliteration': 'qum', 'gloss': 'to arise: establish', '_zh_tw_Gloss': '起來, 就起來', '_es_Gloss': 'Levántate', '_zh_Gloss': '起来, 就起来'}, {'strongNumber': 'H6965J', 'matchingForm': 'קוּם', 'stepTransliteration': 'qum', 'gloss': 'to arise: attack', '_zh_tw_Gloss': '起來, 就起來', '_es_Gloss': 'Levántate', '_zh_Gloss': '起来, 就起来'}, {'strongNumber': 'H6965K', 'matchingForm': 'קוּם', 'stepTransliteration': 'qum', 'gloss': 'to arise: guard', '_zh_tw_Gloss': '起來, 就起來', '_es_Gloss': 'Levántate', '_zh_Gloss': '起来, 就起来'}]","mediumDef":"(Piel) to make cakes, bake cakes, cook bread<BR> § (Piel) to make cakes, bake cakes, cook bread","stepGloss":"to bake","stepTransliteration":"lib.bev","count":2,"_es_Definition":"=","_zh_tw_Definition":"=","_zh_Definition":"=","_step_Type":"word","_zh_tw_Gloss":"=","_es_Gloss":"=","_zh_Gloss":"="}]}