{"vocabInfos":[{"strongNumber":"H5561","accentedUnicode":"סַם","relatedNos":[{"strongNumber":"H1313","matchingForm":"בֹּ֫שֶׂם","stepTransliteration":"bo.sem","gloss":"spice","_zh_tw_Gloss":"香料","_es_Gloss":"aromas","_zh_Gloss":"香料"}],"mediumDef":"1) spice<br>1a) a spice used in incense","stepGloss":"spice","stepTransliteration":"sam","count":16,"_es_Definition":"perfume","_zh_tw_Definition":"1) 香料<br>   1a) 用以作香的一種材料","_zh_Definition":"1) 香料<br>   1a) 用以作香的一种材料","_step_Type":"word","_zh_tw_Gloss":"馨香, 香","_es_Gloss":"aromático","_zh_Gloss":"馨香, 香"}]}