{"vocabInfos":[{"strongNumber":"H7293","accentedUnicode":"רַ֫הַב","relatedNos":[{"strongNumber":"G0124","matchingForm":"Αἰγύπτιος","stepTransliteration":"aiguptios","gloss":"Egyptian","_searchResultRange":"Acts.7.22-Heb.11.29@Gen.12.10-Rev.11.8","_zh_tw_Gloss":"埃及人","_es_Gloss":"egipcio","_zh_Gloss":"埃及人"},{"strongNumber":"G0125","matchingForm":"Αἴγυπτος","stepTransliteration":"aiguptos","gloss":"Egypt","_searchResultRange":"Matt.2.13-Rev.11.8@Gen.12.10-Rev.11.8","_zh_tw_Gloss":"埃及","_es_Gloss":"Egipto","_zh_Gloss":"埃及"},{"strongNumber":"H4693","matchingForm":"מָצוֹר","stepTransliteration":"ma.tsor","gloss":"Egypt","_searchResultRange":"2Kgs.19.24-Mic.7.12@Gen.12.10-Rev.11.8","_zh_tw_Gloss":"埃及","_es_Gloss":"fuertes","_zh_Gloss":"埃及"},{"strongNumber":"H4713","matchingForm":"מִצְרִי","stepTransliteration":"mits.ri","gloss":"Egyptian","_searchResultRange":"Gen.12.12-Ezra.9.1@Gen.12.10-Rev.11.8","_zh_tw_Gloss":"埃及人","_es_Gloss":"Egipcio","_zh_Gloss":"埃及人"},{"strongNumber":"H4714G","matchingForm":"מִצְרַ֫יִם","stepTransliteration":"mits.ra.yim","gloss":"Egypt","_searchResultRange":"Gen.12.10-Zech.14.19@Gen.12.10-Rev.11.8","_zh_tw_Gloss":"埃及","_es_Gloss":"Egipto","_zh_Gloss":"埃及"},{"strongNumber":"H4714H","matchingForm":"מִצְרַ֫יִם","stepTransliteration":"mits.ra.yim","gloss":"Egypt","_searchResultRange":"Gen.10.6-1Chr.1.11","_zh_tw_Gloss":"埃及","_es_Gloss":"Egipto","_zh_Gloss":"埃及"},{"strongNumber":"H4714I","matchingForm":"מִצְרַ֫יִם","stepTransliteration":"mits.ra.yim","gloss":"(Sea of )Egypt","_searchResultRange":"Isa.11.15","_zh_tw_Gloss":"埃及","_es_Gloss":"Egipto","_zh_Gloss":"埃及"},{"strongNumber":"H4714J","matchingForm":"מִצְרַ֫יִם","stepTransliteration":"mits.ra.yim","gloss":" of Egypt","_searchResultRange":"Num.34.5-Isa.27.12@Num.34.5-Ezek.48.28","_zh_tw_Gloss":"埃及","_es_Gloss":"Egipto","_zh_Gloss":"埃及"},{"strongNumber":"H4805H","matchingForm":"מְרִי","stepTransliteration":"me.ri","gloss":"rebellion","_zh_tw_Gloss":"悖逆, 背叛","_es_Gloss":"rebelde","_zh_Gloss":"悖逆, 背叛"}],"mediumDef":"<BR>Another name of <i>mits.ra.yim</i> (מִצְרַ֫יִם \"Egypt\" H4714G) <BR> §  This name is used for: <br> 1) pride, blusterer<br>1a) storm, arrogance (but only as names); emblematic name of Egypt<br>","stepGloss":"Rahab","stepTransliteration":"ra.hav","count":2,"_zh_tw_Definition":"1) 驕傲, 暴風 (只作名字用)<br>    1a1) 神話中的海怪","_zh_Definition":"1) 骄傲, 暴风 (只作名字用)<br>    1a1) 神话中的海怪","_step_Type":"place","_step_Link":"30.108086,31.338220","_stepDetailLexicalTag":"[[\"named\",\"H4714G\",\"Egypt\",630,\"מִצְרַ֫יִם\"],[\"spelled\",\"H4693\",\"Egypt\",5,\"מָצוֹר\"],[\"spelled\",\"H4805G\",\"Egypt\",0,\"מְרִי\"],[\"named\",\"H7293\",\"Rahab\",2,\"רַ֫הַב\"],[\"of a group\",\"H4713\",\"Egyptian\",70,\"מִצְרִי\"],[\"in Greek\",\"G0125\",\"Egypt\",25,\"Αἴγυπτος\"],[\"of a group\",\"G0124\",\"Egyptian\",5,\"Αἰγύπτιος\"]]","_zh_tw_Gloss":"拉哈伯","_es_Gloss":"soberbios","_zh_Gloss":"拉哈伯"}]}