{"vocabInfos":[{"strongNumber":"H7329","accentedUnicode":"רָזָה","relatedNos":[{"strongNumber":"H7330","matchingForm":"רָזֶה","stepTransliteration":"ra.zeh","gloss":"lean","_zh_tw_Gloss":"是瘠薄, 瘦","_es_Gloss":"flaco","_zh_Gloss":"是瘠薄, 瘦"},{"strongNumber":"H7332","matchingForm":"רָזוֹן","stepTransliteration":"ra.zon","gloss":"leanness","_zh_tw_Gloss":"瘦弱, 軟弱","_es_Gloss":"flaqueza","_zh_Gloss":"瘦弱, 软弱"},{"strongNumber":"H7334","matchingForm":"רָזִי","stepTransliteration":"ra.zi","gloss":"wasting","_zh_tw_Gloss":"消滅了","_zh_Gloss":"消灭了"}],"mediumDef":"1) to be or become or grow lean<br>1a) (Qal) to make lean<br>1b) (Niphal) to be made lean","stepGloss":"to starve","stepTransliteration":"ra.zah","count":2,"_es_Definition":"(a) qal   destruir, desolar; (b) nif.   consumir","_zh_tw_Definition":"1) 瘦弱, 變瘦<br>   1a) (Qal) 使之瘦弱 (番 2:11)<br>   1b) (Niphal) 被弄瘦 (賽 17:4)","_zh_Definition":"1) 瘦弱, 变瘦<br>   1a) (Qal) 使之瘦弱 (番 2:11)<br>   1b) (Niphal) 被弄瘦 (赛 17:4)","_step_Type":"verb","_zh_tw_Gloss":"必漸瘦弱","_es_Gloss":"enflaqueceráse","_zh_Gloss":"必渐瘦弱"}]}