{"vocabInfos":[{"strongNumber":"H8327","accentedUnicode":"שָׁרַשׁ","relatedNos":[{"strongNumber":"H8328","matchingForm":"שֹׁ֫רֶשׁ","stepTransliteration":"sho.resh","gloss":"root","_zh_tw_Gloss":"根","_es_Gloss":"raíz","_zh_Gloss":"根"},{"strongNumber":"H8329","matchingForm":"שָׁ֑רֶשׁ","stepTransliteration":"sha.resh","gloss":"Sheresh","_searchResultRange":"1Chr.7.16","_zh_tw_Gloss":"示利施","_es_Gloss":"Seres","_zh_Gloss":"示利施"},{"strongNumber":"H8331","matchingForm":"שַׁרְשָׁה","stepTransliteration":"shar.shah","gloss":"chain","_zh_tw_Gloss":"鍊子","_zh_Gloss":"链子"}],"mediumDef":"1) to uproot, take root, deal with the roots<br>1a) (Piel) to root up, root out<br>1b) (Pual) to be rooted up or out (of produce)<br>1c) (Poel) to take root<br>1d) (Poal) to take root<br>1e) (Hiphil) to take root, cause to take root","stepGloss":"to uproot","stepTransliteration":"sha.rash","count":8,"_es_Definition":"(a) pi.   arrancar, destruir; (b) po.   echar raíces; (c) pu.   ser arrancado de raíz; (d) poal   echar raíces; (e) hif.   echar raíces, prosperar","_zh_tw_Definition":"1) 連根拔除, 連根拔起, 處理根部<br>   1a) (Piel) 根除, 徹底根除<br>   1b) (Pual) (農產品) 被拔起 (伯 31:8)<br>   1c) (Poel) 扎根 (賽 40:24)<br>   1d) (Poal) 扎根 (耶 12:2)<br>   1e) (Hiphil) 扎根, 使扎根","_zh_Definition":"1) 连根拔除, 连根拔起, 处理根部<br>   1a) (Piel) 根除, 彻底根除<br>   1b) (Pual) (农产品) 被拔起 (伯 31:8)<br>   1c) (Poel) 扎根 (赛 40:24)<br>   1d) (Poal) 扎根 (耶 12:2)<br>   1e) (Hiphil) 扎根, 使扎根","_step_Type":"verb","_zh_tw_Gloss":"扎根, 必拔除","_es_Gloss":"raíces","_zh_Gloss":"扎根, 必拔除"}]}