{"vocabInfos":[{"strongNumber":"H8389","accentedUnicode":"תֹּ֫אַר","relatedNos":[{"strongNumber":"H8388A","matchingForm":"תָּאַר","stepTransliteration":"ta.ar","gloss":"to border","_zh_tw_Gloss":"又延到, 劃了模樣","_es_Gloss":"rodea","_zh_Gloss":"又延到, 划了模样"},{"strongNumber":"H8388B","matchingForm":"תָּאַר","stepTransliteration":"ta.ar","gloss":"to delimit","_zh_tw_Gloss":"又延到, 劃了模樣","_es_Gloss":"rodea","_zh_Gloss":"又延到, 划了模样"},{"strongNumber":"H8392","matchingForm":"תֵּבָה","stepTransliteration":"te.vah","gloss":"ark","_zh_tw_Gloss":"方舟","_es_Gloss":"arca","_zh_Gloss":"方舟"},{"strongNumber":"H8396G","matchingForm":"תָּבוֹר","stepTransliteration":"ta.vor","gloss":"Tabor","_searchResultRange":"Josh.19.22-Hos.5.1","_zh_tw_Gloss":"他泊","_es_Gloss":"Tabor","_zh_Gloss":"他泊"},{"strongNumber":"H8396H","matchingForm":"תָּבוֹר","stepTransliteration":"ta.vor","gloss":"Tabor","_searchResultRange":"1Sam.10.3","_zh_tw_Gloss":"他泊","_es_Gloss":"Tabor","_zh_Gloss":"他泊"},{"strongNumber":"H8396I","matchingForm":"תָּבוֹר","stepTransliteration":"ta.vor","gloss":"Tabor","_searchResultRange":"1Chr.6.77@Josh.19.12-1Chr.6.77","_zh_tw_Gloss":"他泊","_es_Gloss":"Tabor","_zh_Gloss":"他泊"}],"mediumDef":"shape, form, outline, figure, appearance","stepGloss":"appearance","stepTransliteration":"to.ar","count":15,"_es_Definition":"forma, apariencia","_zh_tw_Definition":"形狀, 樣式, 輪廓","_zh_Definition":"形状, 样式, 轮廓","_step_Type":"word","_zh_tw_Gloss":"貌, 外貌","_es_Gloss":"parecer","_zh_Gloss":"貌, 外貌"}]}