{"vocabInfos":[{"lsjDefs":" <b>βορρᾶς</b>, -ᾶ (Attic contr. of Βορέας, the North wind personified), <BR /> [in LXX for צָפוֹן ;] <BR /> __1. <b>Boreas, the North wind</b>. <BR /> __2. <b>the north</b>: <ref='Luk.13.29'>Luk.13:29</ref>, <ref='Rev.21.13'>Rev.21:13</ref>.<BR />†  (From Abbott-Smith. LSJ has no entry)","strongNumber":"G1005","accentedUnicode":"βορρᾶς","shortDef":"the north","mediumDef":"<i>primarily</i> <b>the north</b> or <b>N.N.E. wind;</b> <i>metonymy</i> <b>the north,</b> <ref='Luk.13.29'>Lk. 13:29</ref>; <ref='Rev.21.13'>Rev. 21:13</ref>*","stepGloss":"the north","stepTransliteration":"borras","count":2,"_es_Definition":"el norte","_zh_tw_Definition":"北方 (路 13:29; 啟 21:13)","_zh_Definition":"北方 (路 13:29; 启 21:13)","_step_Type":"word","_vi_Definition":"phương bắc","_zh_tw_Gloss":"北, 北邊","_es_Gloss":"el norte ","_zh_Gloss":"北, 北边"}]}