{"vocabInfos":[{"lsjDefs":"<b> ἐξαρτ-ίζω</b>, <br /> <b>complete, finish,</b> τὰς ἡμέρας [<a href=\"javascript:void(0)\" title=\" NT.Act.21.5 \">NT</a>]; <b>finish</b> a building, [<a href=\"javascript:void(0)\" title=\" “IG” 12(2).538 (from Mytilene)\">Refs</a>]; [βιβλία] [<a href=\"javascript:void(0)\" title=\" “POxy.” 296.7 (1st c.AD):\">Refs 1st c.AD+</a>] —<i>passive</i>, πόδες (i.e. τραπέζης) ἕως τῶν κάτω τελέως -ισμένοι [<a href=\"javascript:void(0)\" title=\" 1st c.AD: Josephus Historicus “Antiquitates Judaicae” 3.6.6. \">Refs 1st c.AD+</a>]<br /><Level2><b>__II</b></Level2> <b>equip and dispatch,</b> σκάφας εἰς.. [<a href=\"javascript:void(0)\" title=\" “Periplus Maris Rubri [1st c.AD]” 33:\">Refs</a>] —<i>passive</i>, πλοῖα, γένη,[<a href=\"javascript:void(0)\" title=\" [prev. work]19,14\">Refs</a>]; simply, <b>equip,</b> ναῦς -ισμένας [<a href=\"javascript:void(0)\" title=\" 1st c.BC: Diodorus Siculus Historicus 19.77 \">Refs 1st c.BC+</a>]; <b>furnish, supply,</b> Wilcken [<a href=\"javascript:void(0)\" title=\" “Chr.” 176.10 (1st c.AD)\">Refs 1st c.AD+</a>]:— <i>passive</i>, ἐξηρτισμένον ἅπασι <b>completely furnished,</b> [<a href=\"javascript:void(0)\" title=\" PAmh. 2.93.8 (2nd c.AD)\">Refs 2nd c.AD+</a>]; πρὸς πᾶν ἔργον ἀγαθὸν ἐξηρτισμένος [<a href=\"javascript:void(0)\" title=\" NT.2Tim.3.17 \">NT</a>]: with <i>accusative</i>, <b>provide oneself with,</b> τὰ ἄλλα ἐξήρτιστο [<a href=\"javascript:void(0)\" title=\" 2nd c.AD: Lucianus Sophista “VH” 1.33. \">Refs 2nd c.AD+</a>]","strongNumber":"G1822","accentedUnicode":"ἐξαρτίζω","relatedNos":[{"strongNumber":"G0739","matchingForm":"ἄρτιος","stepTransliteration":"artios","gloss":"competent","_zh_tw_Gloss":"完全","_es_Gloss":"competente","_zh_Gloss":"完全"},{"strongNumber":"G1537","matchingForm":"ἐκ","stepTransliteration":"ek","gloss":"out from","_zh_tw_Gloss":"從","_es_Gloss":"de ","_zh_Gloss":"从"}],"shortDef":"to finish, complete; (<i>passive</i>) to be equipped, furnished","mediumDef":"to finish, complete; (<i>passive</i>) to be equipped, furnished <br /><b>to equip</b>, or <b>furnish completely,</b> <ref='2Ti.3.17'>2Tim. 3:17;</ref> <b>to complete</b> time, <ref='Act.21.5'>Acts 21:5</ref>*","stepGloss":"to finish/furnish","stepTransliteration":"exartizō","count":2,"_es_Definition":"cumplido (de tiempo) ; equipar, preparar,capacitar","_zh_tw_Definition":"1) 完成, 結束 (徒 21:5)<br>2) 裝備好, 佈置好 (提後 3:17)","_zh_Definition":"1) 完成, 结束 (徒 21:5)<br>2) 装备好, 布置好 (提后 3:17)","_step_Type":"verb","_vi_Definition":"làm trọn thành; hoàn thành. ἐκ (G1537) + ἄρτιος (G739)","_zh_tw_Gloss":"滿了, 裝備完整","_es_Gloss":"cumplir/capacitar ","_zh_Gloss":"满了, 装备完整"}]}