{"vocabInfos":[{"lsjDefs":"<b> ἀπόρρηξις</b>, εως, ἡ, <br /> <b>bursting,</b> e.g. of an abscess, [<a href=\"javascript:void(0)\" title=\" 2nd c.AD: Aretaeus Medicus “περὶ αἰτιῶν καὶ σημείων ὀξέων παθῶν” 2.1. \">Refs 2nd c.AD+</a>]<br /><Level3><b>__2</b></Level3> <b>breaking away from,</b> ὁδῶν[<a href=\"javascript:void(0)\" title=\" 1st c.AD: Josephus Historicus “Antiquitates Judaicae” 19.3.1.\">Refs 1st c.AD+</a>]","strongNumber":"G20117","accentedUnicode":"ἀπόρρηξις","shortDef":"breaking away from","mediumDef":"breaking away from","stepGloss":"breaking","stepTransliteration":"aporrēxis","count":0,"_step_Type":"word"}]}