{"vocabInfos":[{"lsjDefs":"<b> δανίζω</b>, <br /> Hellenistic form for δανείζω, [<a href=\"javascript:void(0)\" title=\" LXX.Pro.19.14: \">LXX</a>]<i>future</i> <i>active</i> δανιῶ and <i>middle</i> δανιοῦμαι[<a href=\"javascript:void(0)\" title=\"LXX.Deu.28.12 \">LXX</a>]: <i>aorist</i> <i>participle</i> δανῐσας [<a href=\"javascript:void(0)\" title=\" “Anthologia Graeca” 11.309 (1st c.AD: Lucillius Epigrammaticus), “Lyrica Alexandrina Adespota” 37.27. \">Refs 1st c.AD+</a>]","strongNumber":"G20203","accentedUnicode":"δανίζω","stepGloss":"to lend/borrow","stepTransliteration":"danizō","count":0,"_step_Type":"verb"}]}