{"vocabInfos":[{"lsjDefs":"<b> τραυμᾰτ-ίζω</b>, <br /> <i>Ionic dialect</i> <b>τρωμ-</b>: <i>perfect</i> τετραυμάτικα Decrees cited in [<a href=\"javascript:void(0)\" title=\" 4th c.BC: Demosthenes Orator 18. 155:\">Refs 4th c.BC+</a>] —<i>passive</i> τετραυμάτισμαι (see. below): <i>aorist</i> <i>passive</i> ἐτραυματίσθην [<a href=\"javascript:void(0)\" title=\" 5th c.BC: Euripides Tragicus “Fragmenta” 705 \">Refs 5th c.BC+</a>]:— <b>wound,</b> [<a href=\"javascript:void(0)\" title=\" 5th c.BC: Herodotus Historicus 1.59, +others, 5th c.BC: Euripides Tragicus “Bacchae” 763, “PPetr.” 3p.59 (3rd c.BC), “BGU” 1780.11 (1st c.BC), NT.Luke.20.12, etc.\">NT+5th c.BC+</a>]:—<i>passive</i>, [<a href=\"javascript:void(0)\" title=\" 5th c.BC: Herodotus Historicus 9.61, +others, 5th c.BC: Thucydides Historicus 4.35, etc.; τετραυματισμένον γὰρ ὡς κύων νεβρὸν.. ἐκμαστεύομεν 4th-5th c.BC: Aeschylus Tragicus “Eumenides” 246; τραυματισθεὶς τολλά 5th c.BC: Thucydides Historicus 4.12. \">Refs 5th c.BC+</a>]","strongNumber":"G5135","accentedUnicode":"τραυματίζω","relatedNos":[{"strongNumber":"G5134","matchingForm":"τραῦμα","stepTransliteration":"trauma","gloss":"wound","_zh_tw_Gloss":"傷處","_es_Gloss":"herida","_zh_Gloss":"伤处"}],"shortDef":"to wound","mediumDef":"<b>to wound,</b> <ref='Luk.20.12'>Lk. 20:12</ref>; <ref='Act.19.16'>Acts 19:16</ref>*","stepGloss":"to wound","stepTransliteration":"traumatizō","count":2,"_es_Definition":"herir, lesionar","_zh_tw_Definition":"傷害 (路 10:12; 徒 19:16)","_zh_Definition":"伤害 (路 10:12; 徒 19:16)","_step_Type":"verb","_vi_Definition":"để làm tổn thương; gây thương; gây thương tích","_zh_tw_Gloss":"打傷了, 受了傷","_es_Gloss":"herir","_zh_Gloss":"打伤了, 受了伤"}]}