{"vocabInfos":[{"lsjDefs":"<b> ἐκτίκτω</b>, <br /> <i>aorist 2</i> ἐξέτεκον [<a href=\"javascript:void(0)\" title=\" 4th c.BC: Aristoteles Philosophus “Historia Animalium” 621b20 \">Refs 4th c.BC+</a>]: <i>perfect</i> ἐκτέτοκα [<a href=\"javascript:void(0)\" title=\" 5th-6th c.BC: Plato Philosophus “Theaetetus” 210b \">Refs 5th c.BC+</a>]:—<b>bring forth</b>, [<a href=\"javascript:void(0)\" title=\" 4th c.BC: Aristoteles Philosophus “Historia Animalium” 571b11, +others \">Refs 4th c.BC+</a>]; of fish, <b>spawn</b>, [<a href=\"javascript:void(0)\" title=\"[prev. work] 547a2, 621b20: _metaphorically_, Pl.[same place] \">Refs</a>]","strongNumber":"G7153","accentedUnicode":"ἐκτίκτω","shortDef":"to bring forth","mediumDef":"to bring forth","stepGloss":"to bring forth","stepTransliteration":"ektiktō","count":0,"_step_Type":"verb"}]}