{"vocabInfos":[{"lsjDefs":"<b> ἡνίοχ-ος</b>, <br /> <i>Doric dialect</i> and <i>Aeolic dialect</i> <b>ἀν-</b> [<a href=\"javascript:void(0)\" title=\" 5th c.BC: Pindarus Lyricus “P.” 5.50 \">Refs 5th c.BC+</a>] (variant{ἁν-} as in [<a href=\"javascript:void(0)\" title=\" “N.” 6.66, but compare ἀνιοχίω), 7th-6th c.BC: Sappho Lyrica “Papyrus fragments” in E. Diehl, 20a. 19 \">Refs 7th c.BC+</a>], ὁ: (ἡνία, ἔχω):—<b>one who holds the reins, driver, charioteer</b>, [<a href=\"javascript:void(0)\" title=\" 8th c.BC: Ilias Homerus Epicus “Illiad” 8.89, etc.: sometimes opposed to παραιβάτης, 23.132; ἡ. θεράπων 5.580, 8.119 \">Refs 8th c.BC+</a>]; παρεβεβήκεε δέ οἱ ἡ. [<a href=\"javascript:void(0)\" title=\" 5th c.BC: Herodotus Historicus 7.40. \">Refs 5th c.BC+</a>]<br /><Level3><b>__2</b></Level3> generally, <b>chariot-driver</b>, as in the games, etc., [<a href=\"javascript:void(0)\" title=\" 5th c.BC: Pindarus Lyricus “P.” 5.50, 5th-6th c.BC: Aristophanes Comicus “Pax” 905 (_plural_), 5th-6th c.BC: Xenophon Historicus “Historia Graeca (Hellenica)” 3.2.21, Pl “Phdr.” 254b, “PPetr.” 3p.180 (_plural_, 3rd c.BC)\">Refs 5th c.BC+</a>], etc.; ὑποπτέρων ἵππων ἡ. [<a href=\"javascript:void(0)\" title=\" 5th-6th c.BC: Plato Philosophus “Critias” 116e. \">Refs 5th c.BC+</a>] <br /><Level4><b>__2.b</b></Level4> <b>rider</b>, [<a href=\"javascript:void(0)\" title=\" 6th c.BC: Theognis Elegiacus 260. \">Refs 6th c.BC+</a>]<br /><Level3><b>__3</b></Level3> ὁ ἡ. τῆς νεώς <b>the helmsman</b>, [<a href=\"javascript:void(0)\" title=\" 2nd c.AD(?): Pollianus Epigrammaticus 1.98. \">Refs 2nd c.AD+</a>]<br /><Level3><b>__4</b></Level3> <i>metaphorically</i>, <b>one who guides, governs</b>, χειρῶν καὶ ἰσχύος ἀ. [<a href=\"javascript:void(0)\" title=\" 5th c.BC: Pindarus Lyricus “N.” 6.66 \">Refs 5th c.BC+</a>]; παλαισμοσύνας δεξιὸς ἡ. [<a href=\"javascript:void(0)\" title=\" 4th-5th c.BC: Simonides Lyricus 149; ἡ. τέχνης τραγικῆς “IG” 2.2263 (4th c.BC); παντοίης ἀρετῆς [prev. work]7.2539.2 (from Thebes)\">Refs 4th c.BC+</a>]; ἡ. κιθάρας, of a harper, epigram cited in [<a href=\"javascript:void(0)\" title=\" 5th c.AD(?): Stephanus Byzantius see at {Μίλητος}: _feminine_, αἰγίδος ἡ., of Athena, 5th-6th c.BC: Aristophanes Comicus “Nubes” 602 \">Refs 5th c.BC+</a>]; in Prose with οἷον prefixed, [<a href=\"javascript:void(0)\" title=\" 5th-6th c.BC: Plato Philosophus “Politicus” 266e, etc.\">Refs 5th c.BC+</a>]; of love, [<a href=\"javascript:void(0)\" title=\" 1st-2nd c.AD: Plutarchus Biographus et Philosophus 2.759d, 4th-3rd c.BC: Hermesianax Elegiacus 7.84. \">Refs 4th c.BC+</a>]<br /><Level3><b>__5</b></Level3> as <i>adjective</i>, <b>guiding</b>, γνώμη [<a href=\"javascript:void(0)\" title=\" “Carmen Aureum” 69; ἄνεμοι 4th c.AD(?): Manetho Astrologus 5.153. \">Refs 4th c.AD+</a>]<br /><Level2><b>__II</b></Level2> ἡνίοχοι, οἱ, at Athens, a class of rich citizens <b>who had to furnish chariots</b> for public service, [<a href=\"javascript:void(0)\" title=\" 2nd c.AD: Aelius Dionysius Grammaticus “fragment” 196, 9th c.AD: Photius Legal icographus, etc. \">Refs 2nd c.AD+</a>]<br /><Level2><b>__III</b></Level2> in <i>plural</i>, also,= ἔκφοροι (ἔκφορος [<a href=\"javascript:void(0)\" title=\" 111), [prev. author] \">Refs</a>]<br /><Level2><b>__IV</b></Level2> <b>the constellation Auriga</b>, [<a href=\"javascript:void(0)\" title=\" 4th-3rd c.BC: Aratus Epicus 156, 4th c.BC: Eudoxus Astronomus cited in 2nd c.BC: Hipparchus Astronomicus 1.2.10, etc. \">Refs 4th c.BC+</a>]","strongNumber":"G7633","accentedUnicode":"ἡνίοχος","shortDef":"a charioteer","mediumDef":"a charioteer","stepGloss":"a charioteer","stepTransliteration":"hēniochos","count":0,"_step_Type":"word"}]}