{"vocabInfos":[{"strongNumber":"H0536","accentedUnicode":"אֻמְלַל","relatedNos":[{"strongNumber":"H0535","matchingForm":"אָמַל","stepTransliteration":"a.mal","gloss":"to weaken","_zh_tw_Gloss":"衰殘","_es_Gloss":"enfermó","_zh_Gloss":"衰残"},{"strongNumber":"H0537","matchingForm":"אֲמֵלָל","stepTransliteration":"a.me.lal","gloss":"weak","_zh_tw_Gloss":"那些軟弱","_es_Gloss":"débiles","_zh_Gloss":"那些软弱"}],"mediumDef":"weak, feeble","stepGloss":"weak","stepTransliteration":"um.lal","count":1,"_es_Definition":"decadencia","_zh_tw_Definition":"虛弱的, 無力的 (詩6:2)","_zh_Definition":"虚弱的, 无力的 (诗6:2)","_step_Type":"word","_zh_tw_Gloss":"軟弱","_es_Gloss":"destruída","_zh_Gloss":"软弱"}]}