{"augmentedStrong" : [{"augmentedStrong": "H1138G", "references": "Neh.9.4"}, {"augmentedStrong": "H1138H", "references": "*"}, {"augmentedStrong": "H1138I", "references": "Neh.11.15"}],"vocabinfos": [{"strongNumber":"H1138G","accentedUnicode":"בֻּנִּי","mediumDef":"A man living at the time of Exile and Return, only mentioned at Neh.9.4<BR> § Bunni = \"built\"<br>1) a Levite in the time of Nehemiah<br>2) another Levite of earlier date","stepGloss":"Bunni","stepTransliteration":"bun.ni","count":1,"_es_Definition":"ancestro de Semaías, levita ; (a)   levita; post exílico; (b)   jefe de familia; post exílico","_zh_tw_Definition":"布尼 这个陽性專有名詞在希伯來文的意思是 \"建造\"<br>1) 尼希米時代的一個利未人 (尼9:4)<br>2) 另一利未人 (尼10:15,11:15)","_zh_Definition":"布尼 这个阳性专有名词在希伯来文的意思是 \"建造\"<br>1) 尼希米时代的一个利未人 (尼9:4)<br>2) 另一利未人 (尼10:15,11:15)","_step_Type":"man","_step_Link":"Bunni@Neh.9.4","_zh_tw_Gloss":"布尼","_es_Gloss":"Bunni","_zh_Gloss":"布尼"},{"strongNumber":"H1138H","accentedUnicode":"=","mediumDef":"A man living at the time of Exile and Return, only mentioned at Neh.10.15<BR> § Bunni = \"built\"<br>1) a Levite in the time of Nehemiah<br>2) another Levite of earlier date","stepGloss":"=","stepTransliteration":"=","count":"=","_es_Definition":"=","_zh_tw_Definition":"=","_zh_Definition":"=","_step_Type":"=","_step_Link":"Bunni@Neh.10.15","_zh_tw_Gloss":"=","_es_Gloss":"=","_zh_Gloss":"="},{"strongNumber":"H1138I","accentedUnicode":"=","mediumDef":"A man living at the time of Exile and Return, only mentioned at Neh.11.15; <br> father of: Hashabiah (H2811H)<BR> § Bunni = \"built\"<br>1) a Levite in the time of Nehemiah<br>2) another Levite of earlier date","stepGloss":"=","stepTransliteration":"=","count":"=","_es_Definition":"=","_zh_tw_Definition":"=","_zh_Definition":"=","_step_Type":"=","_step_Link":"Bunni@Neh.11.15","_zh_tw_Gloss":"=","_es_Gloss":"=","_zh_Gloss":"="}]}