{"vocabInfos":[{"strongNumber":"H5686","accentedUnicode":"עָבַת","relatedNos":[{"strongNumber":"H5687","matchingForm":"עָבוֹת","stepTransliteration":"a.vot","gloss":"leafy","_zh_tw_Gloss":"與茂密, 茂密","_es_Gloss":"espeso","_zh_Gloss":"与茂密, 茂密"},{"strongNumber":"H5688","matchingForm":"עֲבֹת","stepTransliteration":"a.vot","gloss":"cord","_zh_tw_Gloss":"索, 繩子","_es_Gloss":"cuerdas","_zh_Gloss":"索, 绳子"}],"mediumDef":"(Piel) to wind, weave, weave together","stepGloss":"to weave","stepTransliteration":"a.vat","count":1,"_es_Definition":"entretejido, denso, espeso (con referencia a árboles de mucho follaje)","_zh_tw_Definition":"(Piel) 轉動, 編織 (彌7:3)","_zh_Definition":"(Piel) 转动, 编织 (弥7:3)","_step_Type":"verb","_zh_tw_Gloss":"彼此結聯","_es_Gloss":"confirman","_zh_Gloss":"彼此结联"}]}