{"vocabInfos":[{"strongNumber":"H7321","accentedUnicode":"רוּעַ","relatedNos":[{"strongNumber":"H7452","matchingForm":"רֵעַ","stepTransliteration":"re.a","gloss":"shouting","_zh_tw_Gloss":"呼喊, 哭號","_es_Gloss":"gritas","_zh_Gloss":"呼喊, 哭号"},{"strongNumber":"H8643","matchingForm":"תְּרוּעָה","stepTransliteration":"te.ru.ah","gloss":"shout","_zh_tw_Gloss":"歡呼, 吶喊","_es_Gloss":"júbilo","_zh_Gloss":"欢呼, 呐喊"}],"mediumDef":"1) to shout, raise a sound, cry out, give a blast<br>1a) (Hiphil)<br>1a1) to shout a war-cry or alarm of battle<br>1a2) to sound a signal for war or march<br>1a3) to shout in triumph (over enemies)<br>1a4) to shout in applause<br>1a5) to shout (with religious impulse)<br>1a6) to cry out in distress<br>1b) (Polal) to utter a shout<br>1c) (Hithpolel)<br>1c1) to shout in triumph<br>1c2) to shout for joy<br>2) (Niphal) destroyed","stepGloss":"to shout","stepTransliteration":"ru.a","count":44,"_es_Definition":"(a) pil.   alegrarse; (b) hitpal.   gritar (de alegría); (c) hif.   gritar, sonar","_zh_tw_Definition":"1) 喊叫, 吹出響聲<br>   1a) (Hiphil)<br>       1a1) 打仗時吆喝或發出警報<br>       1a2) 發出前進或宣戰信號<br>       1a3) (因勝過敵人而) 得意地呼喊<br>       1a4) 喝采<br>       1a5) (發諸宗教情懷) 喊叫<br>       1a6) 悲鳴<br>   1b) (Polal) 叫出來<br>   1c) (Hithpolel)<br>       1c1) 得意洋洋地大叫<br>       1c2) 歡呼<br>2) (Niphal) 遭毀壞 #箴 13:20|","_zh_Definition":"1) 喊叫, 吹出响声<br>   1a) (Hiphil)<br>       1a1) 打仗时吆喝或发出警报<br>       1a2) 发出前进或宣战信号<br>       1a3) (因胜过敌人而) 得意地呼喊<br>       1a4) 喝采<br>       1a5) (发诸宗教情怀) 喊叫<br>       1a6) 悲鸣<br>   1b) (Polal) 叫出来<br>   1c) (Hithpolel)<br>       1c1) 得意洋洋地大叫<br>       1c2) 欢呼<br>2) (Niphal) 遭毁坏 #箴 13:20|","_step_Type":"verb","_zh_tw_Gloss":"喊叫, 吹出響聲","_es_Gloss":"grita","_zh_Gloss":"喊叫, 吹出响声"}]}