{"augmentedStrong" : [{"augmentedStrong": "H7673A", "references": "*"}, {"augmentedStrong": "H7673B", "references": "Lev.23.32 Lev.25.2"}],"vocabinfos": [{"strongNumber":"H7673A","accentedUnicode":"שָׁבַת","relatedNos":"[{'strongNumber': 'H4868', 'matchingForm': 'מִשְׁבָּת', 'stepTransliteration': 'mish.bat', 'gloss': 'annihilation', '_zh_tw_Gloss': '荒涼', '_es_Gloss': 'sábados', '_zh_Gloss': '荒凉'}, {'strongNumber': 'H7673B', 'matchingForm': 'שָׁבַת', 'stepTransliteration': 'sha.vat', 'gloss': 'to keep', '_zh_tw_Gloss': '止息, 必止息', '_es_Gloss': 'cesar', '_zh_Gloss': '止息, 必止息'}, {'strongNumber': 'H7674', 'matchingForm': 'שֶׁ֫בֶת', 'stepTransliteration': 'she.vet', 'gloss': 'cessation', '_zh_tw_Gloss': '受的耽誤, 遠', '_es_Gloss': 'parado', '_zh_Gloss': '受的耽误, 远'}, {'strongNumber': 'H7676', 'matchingForm': 'שַׁבָּת', 'stepTransliteration': 'shab.bat', 'gloss': 'Sabbath', '_zh_tw_Gloss': '安息日', '_es_Gloss': 'sábado', '_zh_Gloss': '安息日'}, {'strongNumber': 'H7677', 'matchingForm': 'שַׁבָּתוֹן', 'stepTransliteration': 'shab.ba.ton', 'gloss': 'sabbath observance', '_zh_tw_Gloss': '守安息日', '_es_Gloss': 'sábado', '_zh_Gloss': '守安息日'}, {'strongNumber': 'H7678G', 'matchingForm': 'שַׁבְּתַי', 'stepTransliteration': 'shab.be.tay', 'gloss': 'Shabbethai', '_searchResultRange': 'Ezra.10.15', '_zh_tw_Gloss': '沙比太', '_es_Gloss': 'Sabethai', '_zh_Gloss': '沙比太'}, {'strongNumber': 'H7678H', 'matchingForm': 'שַׁבְּתַי', 'stepTransliteration': 'shab.be.tay', 'gloss': 'Shabbethai', '_searchResultRange': 'Neh.8.7', '_zh_tw_Gloss': '沙比太', '_es_Gloss': 'Sabethai', '_zh_Gloss': '沙比太'}, {'strongNumber': 'H7678I', 'matchingForm': 'שַׁבְּתַי', 'stepTransliteration': 'shab.be.tay', 'gloss': 'Shabbethai', '_searchResultRange': 'Neh.11.16', '_zh_tw_Gloss': '沙比太', '_es_Gloss': 'Sabethai', '_zh_Gloss': '沙比太'}]","mediumDef":"1) to cease, desist, rest<br>1a) (Qal)<br>1a1) to cease<br>1a2) to rest, desist (from labour)<br>1b) (Niphal) to cease<br>1c) (Hiphil)<br>1c1) to cause to cease, put an end to<br>1c2) to exterminate, destroy<br>1c3) to cause to desist from<br>1c4) to remove<br>1c5) to cause to fail<BR> § 1) to cease, desist, rest<br>1a) (Qal)<br>1a1) to cease<br>1a2) to rest, desist (from labour)<br>1b) (Niphal) to cease<br>1c) (Hiphil)<br>1c1) to cause to cease, put an end to<br>1c2) to exterminate, destroy<br>1c3) to cause to desist from<br>1c4) to remove<br>1c5) to cause to fail","stepGloss":"to cease","stepTransliteration":"sha.vat","count":69,"_es_Definition":"(a) qal   cesar, descansar; (b) nif.   ser detenido; (c) hif.   hacer cesar","_zh_tw_Definition":"1) 中止, 停止, 休息<br>   1a) (Qal)<br>      1a1) 中止<br>      1a2) 休息, 停止 (從勞動中)<br>      1a3) 土地第七年休息<br>      1a4) 遵守 #利 25:2|<br>   1b) (Niphal) 中止<br>   1c) (Hiphil)<br>       1c1) 使之中止, 使終結 <br>       1c2) 撲滅, 毀壞<br>       1c3) 使之休息<br>       1c4) 移除<br>       1c5) 使之失敗<br>2) (Qal) 持續或遵守安息日","_zh_Definition":"1) 中止, 停止, 休息<br>   1a) (Qal)<br>      1a1) 中止<br>      1a2) 休息, 停止 (从劳动中)<br>      1a3) 土地第七年休息<br>      1a4) 遵守 #利 25:2|<br>   1b) (Niphal) 中止<br>   1c) (Hiphil)<br>       1c1) 使之中止, 使终结 <br>       1c2) 扑灭, 毁坏<br>       1c3) 使之休息<br>       1c4) 移除<br>       1c5) 使之失败<br>2) (Qal) 持续或遵守安息日","_step_Type":"verb","_zh_tw_Gloss":"止息, 必止息","_es_Gloss":"cesar","_zh_Gloss":"止息, 必止息"},{"strongNumber":"H7673B","accentedUnicode":"=","relatedNos":"[{'strongNumber': 'H4868', 'matchingForm': 'מִשְׁבָּת', 'stepTransliteration': 'mish.bat', 'gloss': 'annihilation', '_zh_tw_Gloss': '荒涼', '_es_Gloss': 'sábados', '_zh_Gloss': '荒凉'}, {'strongNumber': 'H7673A', 'matchingForm': 'שָׁבַת', 'stepTransliteration': 'sha.vat', 'gloss': 'to cease', '_zh_tw_Gloss': '止息, 必止息', '_es_Gloss': 'cesar', '_zh_Gloss': '止息, 必止息'}, {'strongNumber': 'H7674', 'matchingForm': 'שֶׁ֫בֶת', 'stepTransliteration': 'she.vet', 'gloss': 'cessation', '_zh_tw_Gloss': '受的耽誤, 遠', '_es_Gloss': 'parado', '_zh_Gloss': '受的耽误, 远'}, {'strongNumber': 'H7676', 'matchingForm': 'שַׁבָּת', 'stepTransliteration': 'shab.bat', 'gloss': 'Sabbath', '_zh_tw_Gloss': '安息日', '_es_Gloss': 'sábado', '_zh_Gloss': '安息日'}, {'strongNumber': 'H7677', 'matchingForm': 'שַׁבָּתוֹן', 'stepTransliteration': 'shab.ba.ton', 'gloss': 'sabbath observance', '_zh_tw_Gloss': '守安息日', '_es_Gloss': 'sábado', '_zh_Gloss': '守安息日'}, {'strongNumber': 'H7678G', 'matchingForm': 'שַׁבְּתַי', 'stepTransliteration': 'shab.be.tay', 'gloss': 'Shabbethai', '_searchResultRange': 'Ezra.10.15', '_zh_tw_Gloss': '沙比太', '_es_Gloss': 'Sabethai', '_zh_Gloss': '沙比太'}, {'strongNumber': 'H7678H', 'matchingForm': 'שַׁבְּתַי', 'stepTransliteration': 'shab.be.tay', 'gloss': 'Shabbethai', '_searchResultRange': 'Neh.8.7', '_zh_tw_Gloss': '沙比太', '_es_Gloss': 'Sabethai', '_zh_Gloss': '沙比太'}, {'strongNumber': 'H7678I', 'matchingForm': 'שַׁבְּתַי', 'stepTransliteration': 'shab.be.tay', 'gloss': 'Shabbethai', '_searchResultRange': 'Neh.11.16', '_zh_tw_Gloss': '沙比太', '_es_Gloss': 'Sabethai', '_zh_Gloss': '沙比太'}]","mediumDef":"(Qal) to keep or observe the sabbath<BR> § (Qal) to keep or observe the sabbath","stepGloss":"to keep","stepTransliteration":"=","count":2,"_es_Definition":"sábado, (día de) reposo","_zh_tw_Definition":"=","_zh_Definition":"=","_step_Type":"=","_zh_tw_Gloss":"=","_es_Gloss":"=","_zh_Gloss":"="}]}