{"morphInfos":[{"function":"Verb","functionNotes":"","tense":"Present","voice":"Active","mood":"Subjunctive","person":"2nd","number":"Plural","tenseNotes":"","functionExplained":"an action or activity","tenseExplained":"it is happening in the present","voiceExplained":"it is something one does","moodExplained":"saying that an action might or could happen","personExplained":"they are the ones being spoken or written to","numberExplained":"there are two or more of them","functionDescription":"an action","tenseDescription":"happens","voiceDescription":"- by","moodDescription":"that maybe","personDescription":"being spoken or written to","numberDescription":"persons","description":"_you_ all _maybe do_","explanation":"an action that maybe happens - by persons being spoken or written to"}]}